msca/__init__.py
msca/c2fun/__init__.py
msca/c2fun/main.py
msca/collections/__init__.py
msca/collections/unique_seq.py
msca/integrate/__init__.py
msca/integrate/cython_utils.c
msca/integrate/cython_utils.cpython-312-x86_64-linux-gnu.so
msca/integrate/integration_weights.py
msca/linalg/__init__.py
msca/linalg/matrix.py
msca/metrics/__init__.py
msca/metrics/main.py
msca/metrics/utils.py
msca/optim/__init__.py
msca/optim/line_search/__init__.py
msca/optim/line_search/armijo.py
msca/optim/precon/__init__.py
msca/optim/precon/lbfgs.py
msca/optim/prox/__init__.py
msca/optim/prox/capped_simplex.py
msca/optim/solver/__init__.py
msca/optim/solver/ipsolver.py
msca/optim/solver/ntcgsolver.py
msca/optim/solver/ntsolver.py
msca-0.4.2.dist-info/METADATA
msca-0.4.2.dist-info/WHEEL
msca-0.4.2.dist-info/top_level.txt
msca-0.4.2.dist-info/RECORD
msca-0.4.2.dist-info/licenses/LICENSE
