Metadata-Version: 2.4
Name: msca
Version: 0.4.2
Summary: Mathematical sciences and computational algorithms
Author-email: IHME Math Sciences <ihme.math.sciences@gmail.com>
License: BSD-2-Clause
Project-URL: github, https://github.com/ihmeuw-msca/msca
Classifier: Programming Language :: Python :: 3
Classifier: License :: OSI Approved :: BSD License
Classifier: Natural Language :: English
Requires-Python: <3.13,>=3.11
License-File: LICENSE
Requires-Dist: numpy
Requires-Dist: scipy
Requires-Dist: pydantic
Requires-Dist: scikit-learn
Requires-Dist: pandas
Provides-Extra: test
Requires-Dist: pytest; extra == "test"
Requires-Dist: pytest-cov; extra == "test"
Provides-Extra: docs
Requires-Dist: sphinx; extra == "docs"
Requires-Dist: sphinx-autodoc-typehints; extra == "docs"
Requires-Dist: furo; extra == "docs"
Dynamic: license-file
